pds2/__init__.py
pds2/aipgen/VERSION.txt
pds2/aipgen/__init__.py
pds2/aipgen/aip.py
pds2/aipgen/constants.py
pds2/aipgen/interfaces.py
pds2/aipgen/main.py
pds2/aipgen/registry.py
pds2/aipgen/sip.py
pds2/aipgen/utils.py
pds_deeparchive-2.0.0.dist-info/licenses/LICENSE.md
pds_deeparchive-2.0.0.dist-info/licenses/NOTICE.txt
pds_deeparchive-2.0.0.dist-info/METADATA
pds_deeparchive-2.0.0.dist-info/WHEEL
pds_deeparchive-2.0.0.dist-info/entry_points.txt
pds_deeparchive-2.0.0.dist-info/top_level.txt
pds_deeparchive-2.0.0.dist-info/zip-safe
pds_deeparchive-2.0.0.dist-info/RECORD
