Metadata-Version: 2.4
Name: pds.deeparchive
Version: 2.0.0
Summary: PDS Deep Archive software for generating OAIS AIPs and SIPs for PDS4 Archives
Home-page: https://github.com/NASA-PDS/deep-archive
Download-URL: https://github.com/NASA-PDS/deep-archive/releases/
Author: PDS
Author-email: pds_operator@jpl.nasa.gov
License: apache-2.0
Keywords: PDS,CCSDS,OAIS,AIP,SIP,metadata,submission,archive,package
Classifier: Development Status :: 5 - Production/Stable
Classifier: Environment :: Console
Classifier: Intended Audience :: Science/Research
Classifier: License :: Other/Proprietary License
Classifier: Natural Language :: English
Classifier: Operating System :: OS Independent
Classifier: Programming Language :: Python :: 3 :: Only
Classifier: Programming Language :: Python :: 3.12
Classifier: Programming Language :: Python :: 3.13
Classifier: Topic :: Scientific/Engineering
Requires-Python: >=3.12
License-File: LICENSE.md
License-File: NOTICE.txt
Requires-Dist: setuptools
Requires-Dist: lxml==6.0.0
Requires-Dist: zope.component~=5.0.1
Requires-Dist: zope.interface~=7.1.1
Requires-Dist: requests~=2.31.0
Provides-Extra: dev
Requires-Dist: docutils~=0.21; extra == "dev"
Requires-Dist: sphinx~=8.2.3; extra == "dev"
Requires-Dist: sphinx-rtd-theme==3.0.2; extra == "dev"
Requires-Dist: mypy-zope==1.0.13; extra == "dev"
Requires-Dist: lxml-stubs==0.5.1; extra == "dev"
Requires-Dist: flake8==7.3.0; extra == "dev"
Requires-Dist: flake8-bugbear==24.12.12; extra == "dev"
Requires-Dist: flake8-docstrings==1.7.0; extra == "dev"
Requires-Dist: pep8-naming==0.12.1; extra == "dev"
Requires-Dist: mypy~=1.10.0; extra == "dev"
Requires-Dist: pydocstyle==6.1.1; extra == "dev"
Requires-Dist: coverage==5.5; extra == "dev"
Requires-Dist: pytest==6.2.5; extra == "dev"
Requires-Dist: pytest-cov==5.0.0; extra == "dev"
Requires-Dist: pytest-watch==4.2.0; extra == "dev"
Requires-Dist: pytest-xdist==2.4.0; extra == "dev"
Requires-Dist: pre-commit==2.15.0; extra == "dev"
Requires-Dist: tox~=4.11.0; extra == "dev"
Requires-Dist: types-requests~=2.31.0.20240218; extra == "dev"
Dynamic: download-url
Dynamic: license-file
